py_error-0.0.1.dist-info/METADATA
py_error-0.0.1.dist-info/RECORD
py_error-0.0.1.dist-info/WHEEL
py_error-0.0.1.dist-info/top_level.txt
src/__init__.py
src/pyError/__init__.py
src/pyError/pyError.py
