Metadata-Version: 2.1
Name: py-error
Version: 0.0.1
Summary: An easily-extendable error class for use with python classes
Home-page: https://github.com/justdvnsh/py-error
Author: Divyansh Dwivedi
Author-email: justdvnsh2208@gmail.com
License: UNKNOWN
Platform: UNKNOWN
Classifier: Programming Language :: Python :: 3
Classifier: License :: OSI Approved :: MIT License
Classifier: Operating System :: OS Independent
